pytorch_hyperlight/__init__.py
pytorch_hyperlight/callbacks/__init__.py
pytorch_hyperlight/callbacks/early_stopping.py
pytorch_hyperlight/callbacks/progress.py
pytorch_hyperlight/datasets/__init__.py
pytorch_hyperlight/datasets/cifar.py
pytorch_hyperlight/datasets/base/__init__.py
pytorch_hyperlight/datasets/base/dataloader_builders.py
pytorch_hyperlight/datasets/kaggle/__init__.py
pytorch_hyperlight/datasets/kaggle/utkfaces.py
pytorch_hyperlight/integrations/__init__.py
pytorch_hyperlight/integrations/logging/__init__.py
pytorch_hyperlight/integrations/logging/wandb/__init__.py
pytorch_hyperlight/integrations/logging/wandb/wandb_logger.py
pytorch_hyperlight/metrics/__init__.py
pytorch_hyperlight/metrics/inmem_metric_storage.py
pytorch_hyperlight/metrics/trial_metrics.py
pytorch_hyperlight/runner/__init__.py
pytorch_hyperlight/runner/base_runner.py
pytorch_hyperlight/runner/raytune_runner.py
pytorch_hyperlight/runner/runner.py
pytorch_hyperlight/tasks/__init__.py
pytorch_hyperlight/tasks/classification.py
pytorch_hyperlight/tasks/nst.py
pytorch_hyperlight/utils/__init__.py
pytorch_hyperlight/utils/experiment_trial_namer.py
pytorch_hyperlight/utils/image_utils.py
pytorch_hyperlight/utils/jupyter_nb_utils.py
pytorch_hyperlight/utils/metric_dict_utils.py
pytorch_hyperlight/utils/plot_utils.py
pytorch_hyperlight/utils/random_utils.py
pytorch_hyperlight/utils/request_utils.py
pytorch_hyperlight-0.3.0.dist-info/METADATA
pytorch_hyperlight-0.3.0.dist-info/WHEEL
pytorch_hyperlight-0.3.0.dist-info/top_level.txt
pytorch_hyperlight-0.3.0.dist-info/zip-safe
pytorch_hyperlight-0.3.0.dist-info/RECORD
